portfolio/__init__.py
portfolio/data.py
portfolio/simulation.py
portfolio/test.py
sentiment_algorithm-1.0.2.dist-info/METADATA
sentiment_algorithm-1.0.2.dist-info/WHEEL
sentiment_algorithm-1.0.2.dist-info/top_level.txt
sentiment_algorithm-1.0.2.dist-info/RECORD
